DataPrepKitM/__init__.py
DataPrepKitM-0.1.0.dist-info/LICENCE.txt
DataPrepKitM-0.1.0.dist-info/METADATA
DataPrepKitM-0.1.0.dist-info/WHEEL
DataPrepKitM-0.1.0.dist-info/top_level.txt
DataPrepKitM-0.1.0.dist-info/RECORD
