Metadata-Version: 2.1
Name: DataPrepKitM
Version: 0.1.0
Summary: A series of functions that assist in reading data from a variety of file formats, summarizing datasets, managing missing values, and encoding categorical data.
Author: Mohammad Mrayyan
Author-email: mohammad.t.mrayyan@gmail.com
Classifier: Programming Language :: Python :: 3
Classifier: License :: OSI Approved :: MIT License
Classifier: Operating System :: OS Independent
Requires-Python: >=3.6
License-File: LICENCE.txt
